LICENSE
README.md
setup.cfg
setup.py
fvcore/__init__.py
fvcore.egg-info/PKG-INFO
fvcore.egg-info/SOURCES.txt
fvcore.egg-info/dependency_links.txt
fvcore.egg-info/requires.txt
fvcore.egg-info/top_level.txt
fvcore/common/__init__.py
fvcore/common/benchmark.py
fvcore/common/checkpoint.py
fvcore/common/config.py
fvcore/common/download.py
fvcore/common/file_io.py
fvcore/common/history_buffer.py
fvcore/common/param_scheduler.py
fvcore/common/registry.py
fvcore/common/timer.py
fvcore/nn/__init__.py
fvcore/nn/activation_count.py
fvcore/nn/distributed.py
fvcore/nn/flop_count.py
fvcore/nn/focal_loss.py
fvcore/nn/giou_loss.py
fvcore/nn/jit_analysis.py
fvcore/nn/jit_handles.py
fvcore/nn/parameter_count.py
fvcore/nn/precise_bn.py
fvcore/nn/print_model_statistics.py
fvcore/nn/smooth_l1_loss.py
fvcore/nn/squeeze_excitation.py
fvcore/nn/weight_init.py
fvcore/transforms/__init__.py
fvcore/transforms/transform.py
fvcore/transforms/transform_util.py